HypeCycle.py
hypecycle/HypeCycle.py
hypecycle/__init__.py
hypecycle-0.5.2.dist-info/LICENSE.txt
hypecycle-0.5.2.dist-info/METADATA
hypecycle-0.5.2.dist-info/WHEEL
hypecycle-0.5.2.dist-info/top_level.txt
hypecycle-0.5.2.dist-info/RECORD
