Metadata-Version: 2.1
Name: hypecycle
Version: 0.5.2
Summary: hypecycle is the fundamental package needed for creating, visualizing, and annotating Gartner Hype Cycle with Python
Home-page: https://github.com
Author: Chaolemen Borjigin ,Sun Zhizhong ，zhang Chen
Author-email: chaolemen@ruc.edu.cn
License: BSD 3
Platform: UNKNOWN
Classifier: Programming Language :: Python :: 3
Requires-Dist: numpy (>=1.18)
Requires-Dist: matplotlib (>=3.3)
